{
  "id": "ABI",
  "tile": "pwiz-examples",
  "title": "AB SCIEX",
  "description": "ProteoWizard <code>vendor_readers</code> · AB SCIEX (.wiff) reader-regression files.",
  "files": [
    {
      "url": "https://object.storage.eu01.onstackit.cloud/v09/pwiz-examples/ABI/Reader_ABI_Test.data/7600ZenoTOFMSMS_EAD_TestData-S1.mzML",
      "path": "ABI/Reader_ABI_Test.data/7600ZenoTOFMSMS_EAD_TestData-S1.mzML"
    },
    {
      "url": "https://object.storage.eu01.onstackit.cloud/v09/pwiz-examples/ABI/Reader_ABI_Test.data/Enolase_repeats_AQv1.4.2-20070918_En_04-srmSpectra.mzML",
      "path": "ABI/Reader_ABI_Test.data/Enolase_repeats_AQv1.4.2-20070918_En_04-srmSpectra.mzML"
    },
    {
      "url": "https://object.storage.eu01.onstackit.cloud/v09/pwiz-examples/ABI/Reader_ABI_Test.data/Enolase_repeats_AQv1.4.2-20070918_en_01.mzML",
      "path": "ABI/Reader_ABI_Test.data/Enolase_repeats_AQv1.4.2-20070918_en_01.mzML"
    },
    {
      "url": "https://object.storage.eu01.onstackit.cloud/v09/pwiz-examples/ABI/Reader_ABI_Test.data/Enolase_repeats_AQv1.4.2-20070918_en_02.mzML",
      "path": "ABI/Reader_ABI_Test.data/Enolase_repeats_AQv1.4.2-20070918_en_02.mzML"
    },
    {
      "url": "https://object.storage.eu01.onstackit.cloud/v09/pwiz-examples/ABI/Reader_ABI_Test.data/Enolase_repeats_AQv1.4.2-20070918_en_03.mzML",
      "path": "ABI/Reader_ABI_Test.data/Enolase_repeats_AQv1.4.2-20070918_en_03.mzML"
    },
    {
      "url": "https://object.storage.eu01.onstackit.cloud/v09/pwiz-examples/ABI/Reader_ABI_Test.data/Enolase_repeats_AQv1.4.2-20070918_en_04.mzML",
      "path": "ABI/Reader_ABI_Test.data/Enolase_repeats_AQv1.4.2-20070918_en_04.mzML"
    },
    {
      "url": "https://object.storage.eu01.onstackit.cloud/v09/pwiz-examples/ABI/Reader_ABI_Test.data/Enolase_repeats_AQv1.4.2-20070918_en_05.mzML",
      "path": "ABI/Reader_ABI_Test.data/Enolase_repeats_AQv1.4.2-20070918_en_05.mzML"
    },
    {
      "url": "https://object.storage.eu01.onstackit.cloud/v09/pwiz-examples/ABI/Reader_ABI_Test.data/Enolase_repeats_AQv1.4.2-20070918_en_06.mzML",
      "path": "ABI/Reader_ABI_Test.data/Enolase_repeats_AQv1.4.2-20070918_en_06.mzML"
    },
    {
      "url": "https://object.storage.eu01.onstackit.cloud/v09/pwiz-examples/ABI/Reader_ABI_Test.data/Enolase_repeats_AQv1.4.2-20070918_en_07.mzML",
      "path": "ABI/Reader_ABI_Test.data/Enolase_repeats_AQv1.4.2-20070918_en_07.mzML"
    },
    {
      "url": "https://object.storage.eu01.onstackit.cloud/v09/pwiz-examples/ABI/Reader_ABI_Test.data/Enolase_repeats_AQv1.4.2-20070918_en_08.mzML",
      "path": "ABI/Reader_ABI_Test.data/Enolase_repeats_AQv1.4.2-20070918_en_08.mzML"
    },
    {
      "url": "https://object.storage.eu01.onstackit.cloud/v09/pwiz-examples/ABI/Reader_ABI_Test.data/Enolase_repeats_AQv1.4.2-20070918_en_09.mzML",
      "path": "ABI/Reader_ABI_Test.data/Enolase_repeats_AQv1.4.2-20070918_en_09.mzML"
    },
    {
      "url": "https://object.storage.eu01.onstackit.cloud/v09/pwiz-examples/ABI/Reader_ABI_Test.data/Enolase_repeats_AQv1.4.2-20070918_en_10.mzML",
      "path": "ABI/Reader_ABI_Test.data/Enolase_repeats_AQv1.4.2-20070918_en_10.mzML"
    },
    {
      "url": "https://object.storage.eu01.onstackit.cloud/v09/pwiz-examples/ABI/Reader_ABI_Test.data/PressureTrace1-6500SysSuit1269-globalChromatogramsAreMs1Only.mzML",
      "path": "ABI/Reader_ABI_Test.data/PressureTrace1-6500SysSuit1269-globalChromatogramsAreMs1Only.mzML"
    },
    {
      "url": "https://object.storage.eu01.onstackit.cloud/v09/pwiz-examples/ABI/Reader_ABI_Test.data/PressureTrace1-6500SysSuit1269.mzML",
      "path": "ABI/Reader_ABI_Test.data/PressureTrace1-6500SysSuit1269.mzML"
    },
    {
      "url": "https://object.storage.eu01.onstackit.cloud/v09/pwiz-examples/ABI/Reader_ABI_Test.data/swath.api-sample-centroid.mzML",
      "path": "ABI/Reader_ABI_Test.data/swath.api-sample-centroid.mzML"
    }
  ]
}